histomap/.DS_Store
histomap/__init__.py
histomap/histomap.py
histomap/mergeChannelsRGB.py
histomap/umap.py
histomap-0.1.10.dist-info/METADATA
histomap-0.1.10.dist-info/WHEEL
histomap-0.1.10.dist-info/entry_points.txt
histomap-0.1.10.dist-info/RECORD
