Metadata-Version: 2.4
Name: histomap
Version: 0.1.10
Summary: visualize histology images with umap
Author: Ajit Johnson Nirmal
Author-email: nirmallab@bwh.harvar.edu
Requires-Python: >=3.11
Classifier: Programming Language :: Python :: 3
Classifier: Programming Language :: Python :: 3.11
Classifier: Programming Language :: Python :: 3.12
Classifier: Programming Language :: Python :: 3.13
Classifier: Programming Language :: Python :: 3.14
Requires-Dist: imagecodecs (>=2025.8.2,<2026.0.0)
Requires-Dist: matplotlib (>=3.10.5,<4.0.0)
Requires-Dist: napari (>=0.6.4,<0.7.0)
Requires-Dist: numpy (<=2.2)
Requires-Dist: pandas (>=2.3.1,<3.0.0)
Requires-Dist: pyqt6 (>=6.9.1,<7.0.0)
Requires-Dist: spatialdata (>=0.5.0,<0.6.0)
Requires-Dist: tifffile (<2024.6)
Requires-Dist: umap-learn (>=0.5.9.post2,<0.6.0)
